MANIFEST.in
README.txt
setup.cfg
setup.py
zopeskel.txt
docs/HISTORY.txt
docs/INSTALL.txt
docs/LICENSE.txt
plonetheme/__init__.py
plonetheme.subordinate.egg-info/PKG-INFO
plonetheme.subordinate.egg-info/SOURCES.txt
plonetheme.subordinate.egg-info/dependency_links.txt
plonetheme.subordinate.egg-info/entry_points.txt
plonetheme.subordinate.egg-info/namespace_packages.txt
plonetheme.subordinate.egg-info/not-zip-safe
plonetheme.subordinate.egg-info/paster_plugins.txt
plonetheme.subordinate.egg-info/requires.txt
plonetheme.subordinate.egg-info/top_level.txt
plonetheme/subordinate/README.txt
plonetheme/subordinate/__init__.py
plonetheme/subordinate/configure.zcml
plonetheme/subordinate/overrides.zcml
plonetheme/subordinate/profiles.zcml
plonetheme/subordinate/skins.zcml
plonetheme/subordinate/tests.py
plonetheme/subordinate/version.txt
plonetheme/subordinate/version.txt~
plonetheme/subordinate/browser/__init__.py
plonetheme/subordinate/browser/configure.zcml
plonetheme/subordinate/browser/configure.zcml~
plonetheme/subordinate/browser/interfaces.py
plonetheme/subordinate/browser/login.pt
plonetheme/subordinate/browser/login.pt~
plonetheme/subordinate/browser/login.py
plonetheme/subordinate/browser/login.py~
plonetheme/subordinate/browser/logo.pt
plonetheme/subordinate/browser/logo.pt~
plonetheme/subordinate/browser/overrides.zcml
plonetheme/subordinate/browser/viewlet.pt
plonetheme/subordinate/browser/viewlets.py
plonetheme/subordinate/browser/images/README.txt
plonetheme/subordinate/browser/images/img01.gif
plonetheme/subordinate/browser/images/img03.jpg
plonetheme/subordinate/browser/images/img04.jpg
plonetheme/subordinate/browser/images/img05.gif
plonetheme/subordinate/browser/images/img06.gif
plonetheme/subordinate/browser/images/spacer.gif
plonetheme/subordinate/browser/stylesheets/README.txt
plonetheme/subordinate/browser/stylesheets/README.txt~
plonetheme/subordinate/browser/stylesheets/main.css
plonetheme/subordinate/browser/stylesheets/main.css~
plonetheme/subordinate/profiles/default/cssregistry.xml
plonetheme/subordinate/profiles/default/jsregistry.xml
plonetheme/subordinate/profiles/default/metadata.xml
plonetheme/subordinate/profiles/default/skins.xml
plonetheme/subordinate/profiles/default/viewlets.xml
plonetheme/subordinate/profiles/default/viewlets.xml~
plonetheme/subordinate/skins/plonetheme_subordinate_custom_images/CONTENT.txt
